lucidity/__init__.py
lucidity/_version.py
lucidity/error.py
lucidity/template.py
Lucidity-1.5.1.dist-info/LICENSE.txt
Lucidity-1.5.1.dist-info/METADATA
Lucidity-1.5.1.dist-info/WHEEL
Lucidity-1.5.1.dist-info/top_level.txt
Lucidity-1.5.1.dist-info/RECORD
