Metadata-Version: 2.1
Name: Lucidity
Version: 1.5.1
Summary: Filesystem templating and management.
Home-page: https://gitlab.com/4degrees/lucidity
Author: Martin Pengelly-Phillips
Author-email: martin@4degrees.ltd.uk
License: Apache License (2.0)
Keywords: filesystem,management,templating
Platform: UNKNOWN
